ltsfit/CHANGELOG.rst
ltsfit/LICENSE.txt
ltsfit/README.rst
ltsfit/__init__.py
ltsfit/lts_linefit.py
ltsfit/lts_planefit.py
ltsfit/ltsfit.py
ltsfit/examples/__init__.py
ltsfit/examples/ltsfit_examples.py
ltsfit/examples/ltsfit_python_reference_output.txt
ltsfit-6.0.2.dist-info/METADATA
ltsfit-6.0.2.dist-info/WHEEL
ltsfit-6.0.2.dist-info/top_level.txt
ltsfit-6.0.2.dist-info/zip-safe
ltsfit-6.0.2.dist-info/RECORD
