Metadata-Version: 2.1
Name: ltsfit
Version: 6.0.2
Summary: LtsFit: Least Trimmed Squares Fitting
Home-page: https://purl.org/cappellari/software
Author: Michele Cappellari
Author-email: michele.cappellari@physics.ox.ac.uk
License: Other/Proprietary License
Classifier: Development Status :: 5 - Production/Stable
Classifier: Intended Audience :: Developers
Classifier: Intended Audience :: Science/Research
Classifier: Operating System :: OS Independent
Classifier: Programming Language :: Python :: 3
Requires-Dist: numpy
Requires-Dist: scipy
Requires-Dist: matplotlib
